{
  "annotations": { "list": [] },
  "editable": true,
  "fiscalYearStartMonth": 0,
  "graphTooltip": 1,
  "id": null,
  "links": [],
  "liveNow": false,
  "panels": [
    {
      "datasource": { "type": "prometheus", "uid": "PBFA97CFB590B3BD" },
      "fieldConfig": {
        "defaults": {
          "color": { "mode": "thresholds" },
          "mappings": [],
          "thresholds": { "mode": "absolute", "steps": [ { "color": "green", "value": null } ] }
        }
      },
      "gridPos": { "h": 5, "w": 6, "x": 0, "y": 0 },
      "id": 1,
      "options": {
        "colorMode": "value",
        "graphMode": "area",
        "reduceOptions": { "calcs": [ "lastNotNull" ], "fields": "", "values": false }
      },
      "targets": [
        {
          "datasource": { "type": "prometheus", "uid": "PBFA97CFB590B3BD" },
          "expr": "sum(up)",
          "refId": "A"
        }
      ],
      "title": "Alvos no ar (soma de up)",
      "type": "stat"
    },
    {
      "datasource": { "type": "prometheus", "uid": "PBFA97CFB590B3BD" },
      "fieldConfig": { "defaults": { "unit": "s" } },
      "gridPos": { "h": 5, "w": 6, "x": 6, "y": 0 },
      "id": 2,
      "options": {
        "colorMode": "value",
        "graphMode": "area",
        "reduceOptions": { "calcs": [ "max" ], "fields": "", "values": false }
      },
      "targets": [
        {
          "datasource": { "type": "prometheus", "uid": "PBFA97CFB590B3BD" },
          "expr": "max(probe_duration_seconds)",
          "refId": "A"
        }
      ],
      "title": "Blackbox — maior duração (sondas HTTP)",
      "type": "stat"
    },
    {
      "datasource": { "type": "prometheus", "uid": "PBFA97CFB590B3BD" },
      "fieldConfig": {
        "defaults": { "color": { "mode": "palette-classic" }, "unit": "percent" },
        "overrides": []
      },
      "gridPos": { "h": 9, "w": 12, "x": 0, "y": 5 },
      "id": 3,
      "options": { "legend": { "showLegend": true } },
      "targets": [
        {
          "datasource": { "type": "prometheus", "uid": "PBFA97CFB590B3BD" },
          "expr": "100 * (1 - avg(rate(node_cpu_seconds_total{mode=\"idle\"}[5m])))",
          "legendFormat": "CPU não-idle (média)",
          "refId": "A"
        }
      ],
      "title": "CPU (host, node_exporter)",
      "type": "timeseries"
    },
    {
      "datasource": { "type": "prometheus", "uid": "PBFA97CFB590B3BD" },
      "fieldConfig": { "defaults": { "color": { "mode": "palette-classic" }, "unit": "bytes" } },
      "gridPos": { "h": 9, "w": 12, "x": 12, "y": 5 },
      "id": 4,
      "options": { "legend": { "showLegend": true } },
      "targets": [
        {
          "datasource": { "type": "prometheus", "uid": "PBFA97CFB590B3BD" },
          "expr": "node_memory_MemAvailable_bytes",
          "legendFormat": "Mem disponível",
          "refId": "A"
        }
      ],
      "title": "Memória (host)",
      "type": "timeseries"
    },
    {
      "datasource": { "type": "prometheus", "uid": "PBFA97CFB590B3BD" },
      "fieldConfig": { "defaults": { "color": { "mode": "palette-classic" } } },
      "gridPos": { "h": 9, "w": 24, "x": 0, "y": 14 },
      "id": 5,
      "options": { "legend": { "showLegend": true, "displayMode": "list" } },
      "targets": [
        {
          "datasource": { "type": "prometheus", "uid": "PBFA97CFB590B3BD" },
          "expr": "rate(node_disk_read_bytes_total[5m])",
          "legendFormat": "read {{device}}",
          "refId": "A"
        }
      ],
      "title": "Disco leitura (B/s, node_exporter)",
      "type": "timeseries"
    }
  ],
  "refresh": "15s",
  "schemaVersion": 39,
  "tags": [ "livebridge" ],
  "templating": { "list": [] },
  "time": { "from": "now-1h", "to": "now" },
  "timepicker": {},
  "timezone": "browser",
  "title": "LiveBridge — visão geral",
  "uid": "livebridge-overview",
  "version": 1
}
